{
    "games": [
        {
            "id": "greedyv3",
            "title": "Greedy",
            "description": "A fun Unity WebGL game about collecting fruits",
            "iconPath": "assets/games/greedyv3/game-icon.png",
            "gamePath": "greedyv3",
            "requiredFiles": [
                "index.html",
                "bg.png",
                "game-icon.png",
                "Build/2137007212fbc58ed8342d92f656d3ce.loader.js",
                "Build/b4aa35b7b5acd1c9f06ea04b9e1462fa.data.unityweb",
                "Build/d2822e4a9f0d71c41427f922e253050a.framework.js.unityweb",
                "Build/12299175ab4586e3c7b25c763a664f10.wasm.unityweb",
                "Build/Greedy V3.jpg"
            ],
            "gameParameters": {
                "serverIPWithPort": "ws://147.93.103.135:8001/",
                "unityObjectName": "LevelLoader",
                "unityMethodName": "Initilization"
            }
        }
        
    ]
}